{
  "info": {
    "_postman_id": "event-booking-system",
    "name": "Event Booking System API",
    "description": "Complete API collection for Event Booking System",
    "schema": "https://schema.getpostman.com/json/collection/v2.1.0/collection.json"
  },
  "item": [
    {
      "name": "Authentication",
      "item": [
        {
          "name": "Signup - Customer",
          "request": {
            "method": "POST",
            "header": [
              {
                "key": "Content-Type",
                "value": "application/json"
              }
            ],
            "body": {
              "mode": "raw",
              "raw": "{\n  \"name\": \"John Doe\",\n  \"email\": \"john@example.com\",\n  \"password\": \"password123\",\n  \"role\": \"customer\"\n}"
            },
            "url": {
              "raw": "http://localhost:3000/api/auth/signup",
              "protocol": "http",
              "host": ["localhost"],
              "port": "3000",
              "path": ["api", "auth", "signup"]
            }
          }
        },
        {
          "name": "Signup - Organizer",
          "request": {
            "method": "POST",
            "header": [
              {
                "key": "Content-Type",
                "value": "application/json"
              }
            ],
            "body": {
              "mode": "raw",
              "raw": "{\n  \"name\": \"Jane Smith\",\n  \"email\": \"jane@example.com\",\n  \"password\": \"password123\",\n  \"role\": \"organizer\"\n}"
            },
            "url": {
              "raw": "http://localhost:3000/api/auth/signup",
              "protocol": "http",
              "host": ["localhost"],
              "port": "3000",
              "path": ["api", "auth", "signup"]
            }
          }
        },
        {
          "name": "Login",
          "request": {
            "method": "POST",
            "header": [
              {
                "key": "Content-Type",
                "value": "application/json"
              }
            ],
            "body": {
              "mode": "raw",
              "raw": "{\n  \"email\": \"john@example.com\",\n  \"password\": \"password123\"\n}"
            },
            "url": {
              "raw": "http://localhost:3000/api/auth/login",
              "protocol": "http",
              "host": ["localhost"],
              "port": "3000",
              "path": ["api", "auth", "login"]
            }
          }
        }
      ]
    },
    {
      "name": "Events",
      "item": [
        {
          "name": "Create Event",
          "request": {
            "method": "POST",
            "header": [
              {
                "key": "Content-Type",
                "value": "application/json"
              },
              {
                "key": "Authorization",
                "value": "Bearer YOUR_ORGANIZER_TOKEN"
              }
            ],
            "body": {
              "mode": "raw",
              "raw": "{\n  \"title\": \"Tech Conference 2026\",\n  \"description\": \"Annual technology conference with keynote speakers\",\n  \"date\": \"2026-02-15T10:00:00Z\",\n  \"location\": \"Convention Center, City\",\n  \"totalTickets\": 100,\n  \"ticketPrice\": 50,\n  \"category\": \"technology\"\n}"
            },
            "url": {
              "raw": "http://localhost:3000/api/events",
              "protocol": "http",
              "host": ["localhost"],
              "port": "3000",
              "path": ["api", "events"]
            }
          }
        },
        {
          "name": "Get All Events",
          "request": {
            "method": "GET",
            "header": [],
            "url": {
              "raw": "http://localhost:3000/api/events?status=published",
              "protocol": "http",
              "host": ["localhost"],
              "port": "3000",
              "path": ["api", "events"],
              "query": [
                {
                  "key": "status",
                  "value": "published"
                }
              ]
            }
          }
        },
        {
          "name": "Get Event by ID",
          "request": {
            "method": "GET",
            "header": [],
            "url": {
              "raw": "http://localhost:3000/api/events/EVENT_ID",
              "protocol": "http",
              "host": ["localhost"],
              "port": "3000",
              "path": ["api", "events", "EVENT_ID"]
            }
          }
        },
        {
          "name": "Update Event",
          "request": {
            "method": "PUT",
            "header": [
              {
                "key": "Content-Type",
                "value": "application/json"
              },
              {
                "key": "Authorization",
                "value": "Bearer YOUR_ORGANIZER_TOKEN"
              }
            ],
            "body": {
              "mode": "raw",
              "raw": "{\n  \"ticketPrice\": 75\n}"
            },
            "url": {
              "raw": "http://localhost:3000/api/events/EVENT_ID",
              "protocol": "http",
              "host": ["localhost"],
              "port": "3000",
              "path": ["api", "events", "EVENT_ID"]
            }
          }
        },
        {
          "name": "Publish Event",
          "request": {
            "method": "POST",
            "header": [
              {
                "key": "Authorization",
                "value": "Bearer YOUR_ORGANIZER_TOKEN"
              }
            ],
            "url": {
              "raw": "http://localhost:3000/api/events/EVENT_ID/publish",
              "protocol": "http",
              "host": ["localhost"],
              "port": "3000",
              "path": ["api", "events", "EVENT_ID", "publish"]
            }
          }
        },
        {
          "name": "Delete Event",
          "request": {
            "method": "DELETE",
            "header": [
              {
                "key": "Authorization",
                "value": "Bearer YOUR_ORGANIZER_TOKEN"
              }
            ],
            "url": {
              "raw": "http://localhost:3000/api/events/EVENT_ID",
              "protocol": "http",
              "host": ["localhost"],
              "port": "3000",
              "path": ["api", "events", "EVENT_ID"]
            }
          }
        }
      ]
    },
    {
      "name": "Bookings",
      "item": [
        {
          "name": "Book Tickets",
          "request": {
            "method": "POST",
            "header": [
              {
                "key": "Content-Type",
                "value": "application/json"
              },
              {
                "key": "Authorization",
                "value": "Bearer YOUR_CUSTOMER_TOKEN"
              }
            ],
            "body": {
              "mode": "raw",
              "raw": "{\n  \"eventId\": \"EVENT_ID\",\n  \"quantity\": 2\n}"
            },
            "url": {
              "raw": "http://localhost:3000/api/bookings",
              "protocol": "http",
              "host": ["localhost"],
              "port": "3000",
              "path": ["api", "bookings"]
            }
          }
        },
        {
          "name": "Get My Bookings",
          "request": {
            "method": "GET",
            "header": [
              {
                "key": "Authorization",
                "value": "Bearer YOUR_CUSTOMER_TOKEN"
              }
            ],
            "url": {
              "raw": "http://localhost:3000/api/bookings",
              "protocol": "http",
              "host": ["localhost"],
              "port": "3000",
              "path": ["api", "bookings"]
            }
          }
        },
        {
          "name": "Get Booking by ID",
          "request": {
            "method": "GET",
            "header": [
              {
                "key": "Authorization",
                "value": "Bearer YOUR_TOKEN"
              }
            ],
            "url": {
              "raw": "http://localhost:3000/api/bookings/BOOKING_ID",
              "protocol": "http",
              "host": ["localhost"],
              "port": "3000",
              "path": ["api", "bookings", "BOOKING_ID"]
            }
          }
        },
        {
          "name": "Cancel Booking",
          "request": {
            "method": "PUT",
            "header": [
              {
                "key": "Authorization",
                "value": "Bearer YOUR_CUSTOMER_TOKEN"
              }
            ],
            "url": {
              "raw": "http://localhost:3000/api/bookings/BOOKING_ID/cancel",
              "protocol": "http",
              "host": ["localhost"],
              "port": "3000",
              "path": ["api", "bookings", "BOOKING_ID", "cancel"]
            }
          }
        },
        {
          "name": "Get Event Bookings",
          "request": {
            "method": "GET",
            "header": [
              {
                "key": "Authorization",
                "value": "Bearer YOUR_ORGANIZER_TOKEN"
              }
            ],
            "url": {
              "raw": "http://localhost:3000/api/bookings/event/EVENT_ID/bookings",
              "protocol": "http",
              "host": ["localhost"],
              "port": "3000",
              "path": ["api", "bookings", "event", "EVENT_ID", "bookings"]
            }
          }
        }
      ]
    },
    {
      "name": "Utility",
      "item": [
        {
          "name": "Health Check",
          "request": {
            "method": "GET",
            "header": [],
            "url": {
              "raw": "http://localhost:3000/api/health",
              "protocol": "http",
              "host": ["localhost"],
              "port": "3000",
              "path": ["api", "health"]
            }
          }
        },
        {
          "name": "Process Booking Confirmation Jobs",
          "request": {
            "method": "POST",
            "header": [
              {
                "key": "Content-Type",
                "value": "application/json"
              }
            ],
            "body": {
              "mode": "raw",
              "raw": "{\n  \"jobType\": \"booking-confirmations\"\n}"
            },
            "url": {
              "raw": "http://localhost:3000/api/process-jobs",
              "protocol": "http",
              "host": ["localhost"],
              "port": "3000",
              "path": ["api", "process-jobs"]
            }
          }
        },
        {
          "name": "Process Event Notification Jobs",
          "request": {
            "method": "POST",
            "header": [
              {
                "key": "Content-Type",
                "value": "application/json"
              }
            ],
            "body": {
              "mode": "raw",
              "raw": "{\n  \"jobType\": \"event-notifications\"\n}"
            },
            "url": {
              "raw": "http://localhost:3000/api/process-jobs",
              "protocol": "http",
              "host": ["localhost"],
              "port": "3000",
              "path": ["api", "process-jobs"]
            }
          }
        }
      ]
    }
  ]
}
